{"stat.leaveGame":9,"stat.mineBlock.minecraft.cobblestone":1,"stat.pickup.minecraft.flint":1,"stat.pickup.inspirations.edibles":1,"stat.mineBlock.minecraft.stained_glass_pane":1,"stat.swimOneCm":16892,"stat.mineBlock.charm.barrel":1,"stat.climbOneCm":5023,"stat.useItem.minecraft.planks":3,"stat.pickup.firstaid.bandage":18,"stat.pickup.minecraft.porkchop":3,"stat.useItem.minecraft.dirt":9,"stat.useItem.minecraft.stone_slab2":25,"stat.pickup.minecraft.sand":1,"stat.useItem.spartanweaponry.club_wood":1,"stat.pickup.minecraft.bucket":1,"stat.pickup.minecraft.cobblestone":9,"stat.flyOneCm":26659,"stat.pickup.minecraft.glass_bottle":1,"stat.craftItem.familiarfauna.venison_cooked":2,"stat.pickup.rustic.chili_pepper":6,"stat.mineBlock.minecraft.sand":1,"stat.killEntity.familiarfauna.snail":6,"stat.pickup.minecraft.fish":2,"stat.useItem.minecraft.cooked_beef":2,"stat.useItem.spartanweaponry.battleaxe_wood":16,"stat.pickup.quark.tallow":3,"stat.timeSinceDeath":155673,"stat.useItem.minecraft.wooden_slab":6,"stat.pickup.minecraft.mutton":3,"stat.useItem.notreepunching.knife/flint":8,"stat.useItem.minecraft.potato":7,"stat.furnaceInteraction":12,"stat.pickup.minecraft.beef":7,"stat.craftItem.minecraft.stone_slab2":0,"stat.pickup.lycanitesmobs.spectralboltcharge":1,"stat.pickup.minecraft.hay_block":4,"stat.sprintOneCm":81837,"stat.drop.minecraft.lead":2,"stat.useItem.minecraft.wheat_seeds":150,"stat.pickup.lycanitesmobs.raw_aspid_meat":1,"stat.pickup.rustic.olives":14,"stat.killEntity.familiarfauna.deer":1,"stat.useItem.minecraft.carrot":8,"stat.entityKilledBy.Creeper":1,"stat.deaths":1,"stat.drop":10,"stat.playOneMinute":161549,"stat.killEntity.Sheep":2,"stat.pickup.minecraft.slime_ball":3,"aspid.kill":1,"stat.craftItem.minecraft.dye":3,"stat.mineBlock.minecraft.tallgrass":8,"stat.diveOneCm":19392,"stat.pickup.minecraft.wheat":116,"stat.chestOpened":30,"stat.craftItem.lycanitesmobs.cooked_aspid_meat":1,"stat.killEntity.Slime":1,"stat.pickup.familiarfauna.snail_shell":2,"stat.useItem.lycanitesmobs.cooked_aspid_meat":1,"stat.useItem.notreepunching.rock/stone":1,"stat.jump":471,"stat.fallOneCm":2452,"stat.drop.minecraft.dye":2,"stat.pickup.minecraft.carrot":22,"stat.craftItem.minecraft.bread":12,"stat.mineBlock.rustic.horsetail":2,"stat.crouchOneCm":728,"stat.pickup.minecraft.dirt":13,"stat.pickup.charm.barrel":1,"stat.craftingTableInteraction":13,"stat.pickup.rustic.horsetail":4,"stat.pickup.lycanitesmobs.poisongland":5,"reaper.kill":1,"stat.damageTaken":907,"stat.pickup.notreepunching.rock/stone":19,"stat.pickup.rustic.tomato":14,"stat.pickup.minecraft.dye":2,"stat.pickup.minecraft.planks":3,"stat.pickup.minecraft.bed":4,"tombstone:undead_killed":1,"stat.pickup.minecraft.wheat_seeds":213,"stat.pickup.minecraft.potato":20,"stat.pickup.minecraft.lead":7,"stat.mineBlock.minecraft.gravel":18,"stat.useItem.minecraft.stone_pickaxe":8,"stat.damageDealt":1111,"stat.pickup.simpledifficulty.wool_chestplate":1,"stat.sleepInBed":12,"stat.mineBlock.minecraft.dirt":19,"stat.killEntity.Pig":1,"stat.walkOneCm":619655,"stat.pickup.minecraft.stick":3,"stat.useItem.minecraft.log":2,"stat.useItem.minecraft.cobblestone":1,"spriggan.kill":1,"stat.craftItem.minecraft.wheat":36,"stat.useItem.tombstone.gift":1,"stat.pickup.minecraft.baked_potato":1,"stat.pickup.notreepunching.flint_shard":2,"stat.pickup.minecraft.beetroot":30,"stat.pickup.rustic.marsh_mallow":2,"stat.pickup.rustic.grapes":6,"stat.drop.lycanitesmobs.poisongland":1,"stat.mobKills":14,"stat.pickup.minecraft.book":1,"stat.pickup.lycanitesmobs.lifedraincharge":1,"stat.mineBlock.minecraft.log":1,"stat.pickup.familiarfauna.venison_raw":2,"stat.pickup.minecraft.beetroot_seeds":70,"stat.useItem.minecraft.beetroot_seeds":54,"stat.sneakTime":513,"stat.pickup.minecraft.wool":2,"stat.pickup.rustic.chili_pepper_seeds":2,"stat.drop.firstaid.bandage":5,"stat.mineBlock.minecraft.hay_block":4,"stat.craftItem.notreepunching.knife/flint":1,"stat.mineBlock.minecraft.stone":7}